{
  "meta_title": "Isha West Bengal",
  "nav_links": {
    "home": "Home",
    "about": "About",
    "programs": "Programs",
    "gallery": "Gallery",
    "contact": "Contact"
  },
  "header_title": "Isha West Bengal",
  "disclaimer_text": "This page is just for the upcoming isha programs and events in West Bengal. This does not represent any official website of Isha Foundation.",
  "milestones_title": "Isha Milestones",
  "milestones": [
    "><b>Conscious Planet - Save Soil:</b> Conscious Planet is a global movement that has reached 4.1 billion+ people.",
    "><b>Isha Vidhya:</b> Provides quality education to 9,700+ rural students, with 48% being girls.",
    "><b>Community Health:</b> Over 5 million patients treated through mobile clinics, rural clinics, and free camps.",
    "><b>Save Soil Farmers' Movement:</b> Supports 10,000+ farmers in 580+ villages across 40,000+ acres.",
    "><b>Cauvery Calling:</b> Over 120 million trees planted, boosting farmer incomes by up to 800%."
  ],
  "upcoming_dates_title": "Bangla Programs",
  "upcoming_dates": [
   
    {
      "redirectUrl":"https://chat.whatsapp.com/GyUUDjkMSmHCyhr2huYXZy?mode=ac_t",
      "src": "assets/images/peace.png",
      "date": "<b>September 13-14</b>",
      "location": "<b>Online</b>"
    },
    {
      "redirectUrl":"https://chat.whatsapp.com/GyUUDjkMSmHCyhr2huYXZy?mode=ac_t",
      "src": "assets/images/peace.png",
      "date": "<b>December 20-21</b>",
      "location": "<b>Online</b>"
    }
  ],
  "physical_programs_title": "IEO/OTHER PROGRAMS",
  "physical_programs": [
    {
      "redirectUrl":"https://online.sadhguru.org/event-register?event=inner-engineering-4-days-kolkata-south-28-aug-2025-14239",
      "src": "assets/images/Physical_Programs-1.png",
      "date": "<b>August 28-31</b>",
      "location": "<b>Online</b>",
      "details":"4 Days Inner Engineering (English)"
    }
  ],
  "regular_events_title": "Yearly / Non - Regular Events",
  "regular_events": [
    {
      "name": "MSR",
      "content": "Content"
    }
  ],
  "social_media_title": "Connect With Us",
  "gallery_title": "Gallery of Archived Moments",
  "archives": [
    {
      "src": "assets/images/gallery/1.jpg",
      "alt": "Description of image 1"
    },
    {
      "src": "assets/images/gallery/2.jpg",
      "alt": "Description of image 2"
    },
    {
      "src": "assets/images/gallery/3.jpg",
      "alt": "Description of image 3"
    },
    {
      "src": "assets/images/gallery/image4.jpg",
      "alt": "Description of image 4"
    }
  ],
  "contact_form_title": "CONTACT US",
  "contact_form": {
    "name_label": "Name",
    "email_label": "Email",
    "subject_label": "Subject",
    "message_label": "Message",
    "placeholder_name": "Name",
    "placeholder_email": "Email",
    "placeholder_subject": "Subject",
    "placeholder_message": "Message",
    "button": "Send Message"
  },
  "gmaps_title": "Our Location",
  "gmaps_link": "<iframe src=\"https://www.google.com/maps/embed?pb=!1m18!1m12!1m3!1d3684.66444876935!2d88.43577717596048!3d22.553942033621455!2m3!1f0!2f0!3f0!3m2!1i1024!2i768!4f13.1!3m3!1m2!1s0x3a0276d4990089e5%3A0xc3f6d54238714d2e!2sSalt%20Lake%20Stadium!5e0!3m2!1sen!2sin!4v1717800000000!5m2!1sen!2sin\" width=\"100%\" height=\"450\" style=\"border:0;\" allowfullscreen=\"\" loading=\"lazy\" referrerpolicy=\"no-referrer-when-downgrade\"></iframe>",
  "footer": {
    "copyright": "© 2025 Isha West Bengal. All Rights Reserved. | Terms & Conditions | Privacy Policy",
    "subscribe_title": "Subscribe",
    "subscribe_text": "Join 1.2 Million people from around the world, get wisdom articles delivered in the mailbox for free.",
    "subscribe_button": "Subscribe Now",
    "contact_title": "Contact Us",
    "contact_address": "India<br>Isha Yoga Centre,<br>Velliangiri Foothills,<br>Ishana Vihar Post,<br>Coimbatore, Tamil Nadu - 641114",
    "contact_phone": "+91 83000 83111, 04224283111, 04223538311",
    "contact_email": "support.ishafoundation.org",
    "contact_other_centers": "Other Centres",
    "download_title": "Download Sadhguru App",
    "app_ios": "iOS App",
    "app_android": "Android App"
  }
}